Metadata-Version: 2.1
Name: qinvoke
Version: 0.1.6
Summary: A web gui for running invoke commands.
Home-page: https://github.com/hydiant/qinvoke
Author: Shaoqing Tan
Author-email: tansq7@gmail.com
License: MIT
Platform: UNKNOWN
